amr_um/__init__.py
amr_um/custom_fields.py
amr_um/models.py
amr_um/schemas.py
amr_um-0.0.1rc2.dist-info/LICENSE
amr_um-0.0.1rc2.dist-info/METADATA
amr_um-0.0.1rc2.dist-info/WHEEL
amr_um-0.0.1rc2.dist-info/top_level.txt
amr_um-0.0.1rc2.dist-info/RECORD
