Metadata-Version: 2.1
Name: amr-um
Version: 0.0.1rc2
Summary: Unified Messaging for AMR and MDM systems. A way to enable and simplify multi-utility operations.
Home-page: https://github.com/pwitab/amr-um
Author: Henrik Palmlund Wahlgren @ Palmlund Wahlgren Innovative Technology AB
Author-email: henrik@pwit.se
License: BSD-3
Keywords: AMR,Metering,MDM
Platform: UNKNOWN
Requires-Python: ~=3.6
Requires-Dist: marshmallow (>=3.0.0rc4)
Requires-Dist: attr
